bh_spc/__init__.py
bh_spc/_dump_state.py
bh_spc/_file_version.c
bh_spc/_file_version.cp312-win_amd64.pyd
bh_spc/_file_version.pyx
bh_spc/_ini_files.py
bh_spc/_spcm.pxd
bh_spc/_version.py
bh_spc/_win32_version.pxd
bh_spc/spcm.c
bh_spc/spcm.cp312-win_amd64.pyd
bh_spc/spcm.pyx
pybhspc-0.1.0.dist-info/METADATA
pybhspc-0.1.0.dist-info/WHEEL
pybhspc-0.1.0.dist-info/top_level.txt
pybhspc-0.1.0.dist-info/RECORD
