Metadata-Version: 2.1
Name: pybhspc
Version: 0.1.0
Summary: Control Becker & Hickl SPC modules from Python
Project-URL: Documentation, https://marktsuchida.github.io/pybhspc/
Project-URL: Repository, https://github.com/marktsuchida/pybhspc
Project-URL: Issues, https://github.com/marktsuchida/pybhspc/issues
Keywords: TCSPC,time tagger,BH,Becker & Hickl,SPC,SPCM
Classifier: Intended Audience :: Science/Research
Classifier: License :: OSI Approved :: MIT License
Classifier: Operating System :: Microsoft :: Windows
Classifier: Programming Language :: Python :: 3
Classifier: Programming Language :: Python :: Implementation :: CPython
Classifier: Topic :: Scientific/Engineering
Classifier: Topic :: System :: Hardware :: Hardware Drivers
Requires-Python: >=3.10
Provides-Extra: dev
Requires-Dist: Cython; extra == "dev"
Requires-Dist: matplotlib; extra == "dev"
Requires-Dist: mkdocs; extra == "dev"
Requires-Dist: mkdocs-include-markdown-plugin; extra == "dev"
Requires-Dist: mkdocs-jupyter; extra == "dev"
Requires-Dist: mkdocs-material; extra == "dev"
Requires-Dist: mkdocstrings[python]>=0.19; extra == "dev"
Requires-Dist: nox; extra == "dev"
Requires-Dist: numpy; extra == "dev"
Requires-Dist: pytest; extra == "dev"
Requires-Dist: setuptools; extra == "dev"
Requires-Dist: setuptools_scm; extra == "dev"
Requires-Dist: wheel; extra == "dev"
Provides-Extra: testing
Requires-Dist: pytest>=8.0; extra == "testing"
